<Properties StartupConfiguration="{0DAC8DBF-E31F-4A14-941D-AD79C0D52CE5}|https">
  <MonoDevelop.Ide.DebuggingService.Breakpoints>
    <BreakpointStore />
  </MonoDevelop.Ide.DebuggingService.Breakpoints>
  <MonoDevelop.Ide.Workbench ActiveDocument="CarAuctionBidApi/Program.cs">
    <Files>
      <File FileName="CarAuctionBidApi/Controllers/WeatherForecastController.cs" Line="19" Column="1" />
      <File FileName="CarAuctionBidApi/Dto/BidCalculation/BidCalculationRequestDto.cs" Line="19" Column="4" />
      <File FileName="CarAuctionBidApi/Dto/BidCalculation/BidCalculationResponseDto.cs" Line="8" Column="42" />
      <File FileName="CarAuctionBidApi/Domain/BidCalculation/BidCalculation.cs" Line="32" Column="10" />
      <File FileName="CarAuctionBidApi/Domain/Vehicle/VehicleType.cs" Line="11" Column="2" />
      <File FileName="CarAuctionBidApi/Dto/VehicleTypeDto/VehicleTypeResponseDto.cs" Line="20" Column="1" />
      <File FileName="CarAuctionBidApi/Domain/BidCalculation/BidCalculationFeeParameters.cs" Line="22" Column="1" />
      <File FileName="CarAuctionBidApi/Program.cs" Line="38" Column="11" />
      <File FileName="Tests/Usings.cs" Line="1" Column="1" />
      <File FileName="Tests/Domain/BidCalculation/BidCalculationTest.cs" Line="27" Column="13" />
      <File FileName="Tests/Dto/VehicleTypeDtoTest/VehicleTypeDtoTest.cs" Line="9" Column="9" />
      <File FileName="Tests/Dto/BidCalculationDtoTest/BidCalculationRequestDtoTest.cs" Line="10" Column="9" />
      <File FileName="Tests/Dto/BidCalculationDtoTest/BidCalculationResponseDtoTest.cs" Line="27" Column="1" />
      <File FileName="CarAuctionBidApi/appsettings.json" Line="1" Column="1" />
      <File FileName="CarAuctionBidApi/Properties/launchSettings.json" Line="41" Column="2" />
    </Files>
    <Pads>
      <Pad Id="ProjectPad">
        <State name="__root__">
          <Node name="CarAuctionBidApi" expanded="True">
            <Node name="CarAuctionBidApi" expanded="True">
              <Node name="Dependencies" expanded="True">
                <Node name="PackageDependencies" expanded="True" />
              </Node>
              <Node name="Properties" expanded="True" />
              <Node name="appsettings.json" expanded="True" />
            </Node>
            <Node name="Tests" expanded="True" />
          </Node>
        </State>
      </Pad>
      <Pad Id="MonoDevelop.Debugger.WatchPad">
        <State />
      </Pad>
      <Pad Id="MonoDevelop.UnitTesting.TestPad">
        <State name="__root__">
          <Node name="CarAuctionBidApi" expanded="True" />
        </State>
      </Pad>
    </Pads>
  </MonoDevelop.Ide.Workbench>
  <MultiItemStartupConfigurations />
  <MonoDevelop.Ide.ItemProperties.CarAuctionBidApi PreferredExecutionTarget="/Applications/Firefox.app" />
  <MonoDevelop.Ide.DebuggingService.PinnedWatches />
  <MonoDevelop.Ide.Workspace ActiveConfiguration="Debug" />
</Properties>